TextMatcher-0.12.dist-info/METADATA
TextMatcher-0.12.dist-info/RECORD
TextMatcher-0.12.dist-info/WHEEL
TextMatcher-0.12.dist-info/top_level.txt
tests/__init__.py
tests/conftest.py
tests/test_pdf_match.py
tests/test_webpage_match.py
textmatcher/__init__.py
textmatcher/program.py
