Metadata-Version: 2.1
Name: TextMatcher
Version: 0.12
Summary: Extract data from an web-page or PDF-document and match it with the given text parameter
Home-page: https://github.com/maykinmedia/python-textmatcher
Author: Maykin Media
Author-email: support@maykinmedia.nl
License: MIT
Keywords: textmatcher
Platform: UNKNOWN
Classifier: Development Status :: 3 - Alpha
Classifier: Intended Audience :: Developers
Classifier: Operating System :: Unix
Classifier: Operating System :: MacOS
Classifier: Operating System :: Microsoft :: Windows
Classifier: Programming Language :: Python :: 3.6
Classifier: Topic :: Software Development :: Libraries :: Python Modules
Provides-Extra: tests
Provides-Extra: pep8
Provides-Extra: docs
Provides-Extra: coverage
Provides-Extra: release
Requires-Dist: requests
Requires-Dist: beautifulsoup4
Requires-Dist: pdfminer.six
Provides-Extra: coverage
Requires-Dist: pytest-cov; extra == 'coverage'
Provides-Extra: docs
Requires-Dist: sphinx; extra == 'docs'
Requires-Dist: sphinx-rtd-theme; extra == 'docs'
Provides-Extra: pep8
Requires-Dist: flake8; extra == 'pep8'
Provides-Extra: release
Requires-Dist: zest.releaser; extra == 'release'
Provides-Extra: tests
Requires-Dist: pytest; extra == 'tests'
Requires-Dist: tox; extra == 'tests'
Requires-Dist: isort; extra == 'tests'
